AUTHOR.txt
CHANGES.txt
LICENSE.txt
README.txt
TODO.txt
bootstrap.py
buildout.cfg
setup.py
src/z3c/__init__.py
src/z3c.skin.pagelet.egg-info/PKG-INFO
src/z3c.skin.pagelet.egg-info/SOURCES.txt
src/z3c.skin.pagelet.egg-info/dependency_links.txt
src/z3c.skin.pagelet.egg-info/namespace_packages.txt
src/z3c.skin.pagelet.egg-info/not-zip-safe
src/z3c.skin.pagelet.egg-info/requires.txt
src/z3c.skin.pagelet.egg-info/top_level.txt
src/z3c/skin/__init__.py
src/z3c/skin/pagelet/README.txt
src/z3c/skin/pagelet/SETUP.cfg
src/z3c/skin/pagelet/__init__.py
src/z3c/skin/pagelet/configure.zcml
src/z3c/skin/pagelet/ftesting.zcml
src/z3c/skin/pagelet/interfaces.py
src/z3c/skin/pagelet/menu.py
src/z3c/skin/pagelet/menu.zcml
src/z3c/skin/pagelet/menu_tab.pt
src/z3c/skin/pagelet/menu_tab_item.pt
src/z3c/skin/pagelet/testing.py
src/z3c/skin/pagelet/tests.py
src/z3c/skin/pagelet/z3c.skin.pagelet-configure.zcml
src/z3c/skin/pagelet/browser/__init__.py
src/z3c/skin/pagelet/browser/configure.zcml
src/z3c/skin/pagelet/browser/favicon.png
src/z3c/skin/pagelet/browser/form.pt
src/z3c/skin/pagelet/browser/index.pt
src/z3c/skin/pagelet/browser/mockup.png
src/z3c/skin/pagelet/browser/navigation.pt
src/z3c/skin/pagelet/browser/pagelet.css
src/z3c/skin/pagelet/browser/template.pt
src/z3c/skin/pagelet/browser/title.pt
src/z3c/skin/pagelet/browser/views.py
src/z3c/skin/pagelet/browser/widget.pt
src/z3c/skin/pagelet/browser/img/background.gif
src/z3c/skin/pagelet/browser/img/buttonBG.gif
src/z3c/skin/pagelet/browser/img/logo.gif
src/z3c/skin/pagelet/browser/img/menuBG.jpg
src/z3c/skin/pagelet/browser/img/menuSeparator.gif
src/z3c/skin/pagelet/browser/img/topBG.jpg
