Metadata-Version: 1.0
Name: z3c.skin.pagelet
Version: 1.0.1
Summary: A base skin for pagelet-based UIs
Home-page: http://cheeseshop.python.org/pypi/z3c.skin.pagelet
Author: Roger Ineichen and the Zope Community
Author-email: zope3-dev@zope.org
License: ZPL 2.1
Keywords: zope3 pagelet skin
Platform: UNKNOWN
Classifier: Development Status :: 5 - Production/Stable
Classifier: Environment :: Web Environment
Classifier: Intended Audience :: Developers
Classifier: License :: OSI Approved :: Zope Public License
Classifier: Programming Language :: Python
Classifier: Natural Language :: English
Classifier: Operating System :: OS Independent
Classifier: Topic :: Internet :: WWW/HTTP
Classifier: Framework :: Zope3
